MANIFEST.in
README.rst
setup.py
eyeball/__init__.py
eyeball/__main__.py
eyeball/core.py
eyeball.egg-info/PKG-INFO
eyeball.egg-info/SOURCES.txt
eyeball.egg-info/dependency_links.txt
eyeball.egg-info/not-zip-safe
eyeball.egg-info/top_level.txt